tree_sitter_devicetree/__init__.py
tree_sitter_devicetree/__init__.pyi
tree_sitter_devicetree/_binding.pyd
tree_sitter_devicetree/binding.c
tree_sitter_devicetree/py.typed
tree_sitter_devicetree/queries/highlights.scm
tree_sitter_devicetree-0.14.1.dist-info/LICENSE
tree_sitter_devicetree-0.14.1.dist-info/METADATA
tree_sitter_devicetree-0.14.1.dist-info/WHEEL
tree_sitter_devicetree-0.14.1.dist-info/top_level.txt
tree_sitter_devicetree-0.14.1.dist-info/RECORD
