Metadata-Version: 2.2
Name: tree-sitter-devicetree
Version: 0.14.1
Summary: Tree-sitter parser for Devicetree files, with support for Zephyr's superset of Devicetree syntax.
Author: Joel Spadin
License: MIT
Project-URL: Homepage, https://github.com/joelspadin/tree-sitter-devicetree
Keywords: incremental,parsing,tree-sitter,devicetree
Classifier: Intended Audience :: Developers
Classifier: License :: OSI Approved :: MIT License
Classifier: Topic :: Software Development :: Compilers
Classifier: Topic :: Text Processing :: Linguistic
Classifier: Typing :: Typed
Requires-Python: >=3.10
License-File: LICENSE
Provides-Extra: core
Requires-Dist: tree-sitter~=0.24; extra == "core"
